speedo/__init__.py
speedo/pants.py
speedo/algorithms/__init__.py
speedo/algorithms/calculations/__init__.py
speedo/algorithms/calculations/common.py
speedo/algorithms/calculations/discrete.py
speedo/algorithms/regression/__init__.py
speedo/algorithms/regression/bezier.py
speedo/algorithms/regression/constants.py
speedo/algorithms/regression/describe.py
speedo/algorithms/regression/funcs.py
speedo/algorithms/regression/matrices.py
speedo/algorithms/regression/modules.py
speedo/algorithms/regression/mono.py
speedo/algorithms/regression/regress.py
speedo/algorithms/sketch/__init__.py
speedo/algorithms/sketch/data.py
speedo/algorithms/sketch/outliers.py
speedo/algorithms/sketch/settings.py
speedo/algorithms/sketch/theme.py
speedo-1.0.6.dist-info/LICENSE
speedo-1.0.6.dist-info/METADATA
speedo-1.0.6.dist-info/WHEEL
speedo-1.0.6.dist-info/top_level.txt
speedo-1.0.6.dist-info/RECORD
